Metadata-Version: 2.1
Name: odoo9-addon-l10n-ch-lsv-dd
Version: 9.0.1.0.0.99.dev40
Summary: Create LSV and Direct Debit (postfinance) files
Home-page: http://www.compassion.ch,http://www.braintec-group.com
Author: brain-tec AG,Compassion,Odoo Community Association (OCA)
Author-email: support@odoo-community.org
License: AGPL-3
Platform: UNKNOWN
Classifier: Programming Language :: Python
Classifier: Framework :: Odoo
Classifier: Framework :: Odoo :: 9.0
Classifier: License :: OSI Approved :: GNU Affero General Public License v3
Requires-Python: ~=2.7
Requires-Dist: odoo9-addon-account-banking-mandate
Requires-Dist: odoo9-addon-account-banking-pain-base
Requires-Dist: odoo9-addon-account-banking-sepa-direct-debit
Requires-Dist: odoo9-addon-account-payment-mode
Requires-Dist: odoo9-addon-account-payment-order
Requires-Dist: odoo9-addon-l10n-ch-payment-slip
Requires-Dist: odoo (<9.1a,>=9.0a)
